{
  "lang":"en",
  "name":"pipeline",
  "version":"0.0.0",
  "spacy_version":">=3.7.5,<3.8.0",
  "description":"",
  "author":"",
  "email":"",
  "url":"",
  "license":"",
  "spacy_git_version":"a6d0fc360",
  "vectors":{
    "width":0,
    "vectors":0,
    "keys":0,
    "name":null,
    "mode":"default"
  },
  "labels":{
    "tok2vec":[

    ],
    "ner":[
      "H_SKILL",
      "LANG_FRAM",
      "REQUIREMENT",
      "S_SKILL"
    ]
  },
  "pipeline":[
    "tok2vec",
    "ner"
  ],
  "components":[
    "tok2vec",
    "ner"
  ],
  "disabled":[

  ],
  "performance":{
    "ents_f":0.3930211203,
    "ents_p":0.4766146993,
    "ents_r":0.334375,
    "ents_per_type":{
      "H_SKILL":{
        "p":0.1960784314,
        "r":0.1648351648,
        "f":0.1791044776
      },
      "S_SKILL":{
        "p":0.4296296296,
        "r":0.267281106,
        "f":0.3295454545
      },
      "REQUIREMENT":{
        "p":0.7857142857,
        "r":0.5789473684,
        "f":0.6666666667
      },
      "LANG_FRAM":{
        "p":0.7819548872,
        "r":0.5123152709,
        "f":0.619047619
      }
    },
    "tok2vec_loss":149338.6437835627,
    "ner_loss":122.6227008513
  }
}